snap4n6/__init__.py
snap4n6/__main__.py
snap4n6/cli.py
snap4n6-0.4.2.dist-info/LICENSE
snap4n6-0.4.2.dist-info/METADATA
snap4n6-0.4.2.dist-info/WHEEL
snap4n6-0.4.2.dist-info/entry_points.txt
snap4n6-0.4.2.dist-info/top_level.txt
snap4n6-0.4.2.dist-info/RECORD
