Metadata-Version: 2.1
Name: snap4n6
Version: 0.4.2
Summary: Rebuild Elastic Block Storage (EBS) direct API blocks into a DD forensic image generated by Snap4n6 Serverless Imager.
Home-page: https://github.com/4n6ir/snap4n6cli
Author: John Lukach
Author-email: hello@lukach.io
License: Apache-2.0
Requires-Python: >=3.7
License-File: LICENSE
Requires-Dist: boto3
Requires-Dist: tqdm
